[
    {
        "acq_date": "2022-04-28",
        "lat": -32.802279999999996,
        "lng": -70.95315
    },
    {
        "acq_date": "2022-04-28",
        "lat": -32.8003,
        "lng": -70.95478
    },
    {
        "acq_date": "2022-04-28",
        "lat": -32.80134,
        "lng": -70.95003
    },
    {
        "acq_date": "2022-04-28",
        "lat": -33.295390000000005,
        "lng": -70.72775
    },
    {
        "acq_date": "2022-04-28",
        "lat": -34.10407,
        "lng": -70.45716999999999
    },
    {
        "acq_date": "2022-04-28",
        "lat": -36.47124,
        "lng": -70.3931
    },
    {
        "acq_date": "2022-04-28",
        "lat": -28.480359999999997,
        "lng": -71.25024
    },
    {
        "acq_date": "2022-04-28",
        "lat": -50.65744,
        "lng": -71.19119
    },
    {
        "acq_date": "2022-04-28",
        "lat": -34.10938,
        "lng": -70.4552
    },
    {
        "acq_date": "2022-04-28",
        "lat": -32.80259,
        "lng": -70.95369000000001
    },
    {
        "acq_date": "2022-04-28",
        "lat": -32.806290000000004,
        "lng": -70.95107
    },
    {
        "acq_date": "2022-04-28",
        "lat": -43.61026,
        "lng": -71.42919
    },
    {
        "acq_date": "2022-04-28",
        "lat": -36.74418,
        "lng": -73.12437
    },
    {
        "acq_date": "2022-04-28",
        "lat": -36.74852,
        "lng": -73.12581999999999
    },
    {
        "acq_date": "2022-04-28",
        "lat": -36.231770000000004,
        "lng": -72.09583
    },
    {
        "acq_date": "2022-04-28",
        "lat": -36.23264,
        "lng": -72.09931
    },
    {
        "acq_date": "2022-04-28",
        "lat": -36.2066,
        "lng": -72.12415
    },
    {
        "acq_date": "2022-04-28",
        "lat": -35.989020000000004,
        "lng": -72.18708000000001
    }
]