[
    {
        "acq_date": "2022-05-23",
        "lat": -23.78004,
        "lng": -70.31676999999999
    },
    {
        "acq_date": "2022-05-23",
        "lat": -23.78337,
        "lng": -70.31741
    },
    {
        "acq_date": "2022-05-23",
        "lat": -23.82125,
        "lng": -70.31676999999999
    },
    {
        "acq_date": "2022-05-23",
        "lat": -23.824579999999997,
        "lng": -70.3174
    },
    {
        "acq_date": "2022-05-23",
        "lat": -23.8252,
        "lng": -70.31359
    },
    {
        "acq_date": "2022-05-23",
        "lat": -27.35695,
        "lng": -70.22079000000001
    },
    {
        "acq_date": "2022-05-23",
        "lat": -27.41524,
        "lng": -70.25966
    },
    {
        "acq_date": "2022-05-23",
        "lat": -27.419159999999998,
        "lng": -70.25641999999999
    },
    {
        "acq_date": "2022-05-23",
        "lat": -28.48132,
        "lng": -71.25014
    },
    {
        "acq_date": "2022-05-23",
        "lat": -27.859720000000003,
        "lng": -70.16724
    },
    {
        "acq_date": "2022-05-23",
        "lat": -27.86028,
        "lng": -70.17155
    },
    {
        "acq_date": "2022-05-23",
        "lat": -27.86085,
        "lng": -70.17586
    },
    {
        "acq_date": "2022-05-23",
        "lat": -27.856240000000003,
        "lng": -70.16787
    },
    {
        "acq_date": "2022-05-23",
        "lat": -27.85681,
        "lng": -70.17215999999999
    },
    {
        "acq_date": "2022-05-23",
        "lat": -27.852759999999996,
        "lng": -70.16845
    },
    {
        "acq_date": "2022-05-23",
        "lat": -27.49557,
        "lng": -70.38139
    },
    {
        "acq_date": "2022-05-23",
        "lat": -27.492070000000002,
        "lng": -70.38204
    },
    {
        "acq_date": "2022-05-24",
        "lat": -36.74342,
        "lng": -73.12788
    },
    {
        "acq_date": "2022-05-24",
        "lat": -23.78377,
        "lng": -70.31873
    },
    {
        "acq_date": "2022-05-24",
        "lat": -23.7838,
        "lng": -70.31736
    },
    {
        "acq_date": "2022-05-24",
        "lat": -23.821720000000003,
        "lng": -70.31754000000001
    },
    {
        "acq_date": "2022-05-24",
        "lat": -27.35657,
        "lng": -70.22404
    },
    {
        "acq_date": "2022-05-24",
        "lat": -27.41508,
        "lng": -70.26236
    },
    {
        "acq_date": "2022-05-24",
        "lat": -27.41988,
        "lng": -70.25798
    },
    {
        "acq_date": "2022-05-24",
        "lat": -16.53872,
        "lng": -72.07764
    },
    {
        "acq_date": "2022-05-25",
        "lat": -23.81985,
        "lng": -70.31839000000001
    },
    {
        "acq_date": "2022-05-25",
        "lat": -27.413690000000003,
        "lng": -70.26119
    },
    {
        "acq_date": "2022-05-25",
        "lat": -27.41445,
        "lng": -70.2579
    },
    {
        "acq_date": "2022-05-25",
        "lat": -32.80069,
        "lng": -70.94973
    },
    {
        "acq_date": "2022-05-25",
        "lat": -32.7593,
        "lng": -71.47719000000001
    },
    {
        "acq_date": "2022-05-25",
        "lat": -36.49445,
        "lng": -72.82779000000001
    },
    {
        "acq_date": "2022-05-25",
        "lat": -36.512809999999995,
        "lng": -72.81389
    },
    {
        "acq_date": "2022-05-25",
        "lat": -36.49467,
        "lng": -72.82829
    },
    {
        "acq_date": "2022-05-25",
        "lat": -36.51315,
        "lng": -72.81443
    },
    {
        "acq_date": "2022-05-25",
        "lat": -17.431720000000002,
        "lng": -70.00236
    },
    {
        "acq_date": "2022-05-25",
        "lat": -17.43209,
        "lng": -70.00584
    },
    {
        "acq_date": "2022-05-25",
        "lat": -17.08309,
        "lng": -71.75661
    },
    {
        "acq_date": "2022-05-25",
        "lat": -37.59389,
        "lng": -71.97612
    },
    {
        "acq_date": "2022-05-25",
        "lat": -37.589690000000004,
        "lng": -71.98136
    },
    {
        "acq_date": "2022-05-25",
        "lat": -35.84944,
        "lng": -72.00034000000001
    },
    {
        "acq_date": "2022-05-25",
        "lat": -35.26554,
        "lng": -72.00064
    },
    {
        "acq_date": "2022-05-25",
        "lat": -32.80512,
        "lng": -70.94848
    },
    {
        "acq_date": "2022-05-25",
        "lat": -32.825390000000006,
        "lng": -71.09727
    },
    {
        "acq_date": "2022-05-25",
        "lat": -30.76882,
        "lng": -70.92229
    },
    {
        "acq_date": "2022-05-25",
        "lat": -38.689029999999995,
        "lng": -72.41709
    },
    {
        "acq_date": "2022-05-25",
        "lat": -38.09672,
        "lng": -70.79536
    },
    {
        "acq_date": "2022-05-25",
        "lat": -37.58952,
        "lng": -71.97948000000001
    },
    {
        "acq_date": "2022-05-25",
        "lat": -37.40364,
        "lng": -72.55729000000001
    },
    {
        "acq_date": "2022-05-25",
        "lat": -37.39931,
        "lng": -72.55877
    },
    {
        "acq_date": "2022-05-25",
        "lat": -37.39497,
        "lng": -72.56023
    },
    {
        "acq_date": "2022-05-25",
        "lat": -36.51826,
        "lng": -72.8101
    },
    {
        "acq_date": "2022-05-25",
        "lat": -36.51611,
        "lng": -72.81335
    },
    {
        "acq_date": "2022-05-25",
        "lat": -35.85349,
        "lng": -71.99931
    },
    {
        "acq_date": "2022-05-25",
        "lat": -35.84885,
        "lng": -72.00079000000001
    },
    {
        "acq_date": "2022-05-25",
        "lat": -35.35706,
        "lng": -71.77346999999999
    },
    {
        "acq_date": "2022-05-25",
        "lat": -35.269,
        "lng": -71.99795999999999
    },
    {
        "acq_date": "2022-05-25",
        "lat": -32.8035,
        "lng": -70.95213000000001
    },
    {
        "acq_date": "2022-05-25",
        "lat": -30.76843,
        "lng": -70.91998000000001
    },
    {
        "acq_date": "2022-05-25",
        "lat": -30.84233,
        "lng": -71.30523000000001
    },
    {
        "acq_date": "2022-05-25",
        "lat": -30.7704,
        "lng": -70.91807
    },
    {
        "acq_date": "2022-05-25",
        "lat": -30.84194,
        "lng": -71.30438000000001
    },
    {
        "acq_date": "2022-05-25",
        "lat": -27.4183,
        "lng": -70.25779
    }
]