[
    {
        "acq_date": "2022-01-27",
        "lat": -23.82484,
        "lng": -70.31308
    },
    {
        "acq_date": "2022-01-27",
        "lat": -23.82627,
        "lng": -70.32294
    },
    {
        "acq_date": "2022-01-27",
        "lat": -38.02941,
        "lng": -72.54163
    },
    {
        "acq_date": "2022-01-27",
        "lat": -34.1097,
        "lng": -70.45888000000001
    },
    {
        "acq_date": "2022-01-27",
        "lat": -33.10583,
        "lng": -70.63852
    },
    {
        "acq_date": "2022-01-27",
        "lat": -37.03633,
        "lng": -72.38251
    },
    {
        "acq_date": "2022-01-27",
        "lat": -38.32483,
        "lng": -70.98975
    },
    {
        "acq_date": "2022-01-27",
        "lat": -38.30192,
        "lng": -72.28992
    },
    {
        "acq_date": "2022-01-27",
        "lat": -45.58657,
        "lng": -72.05776
    },
    {
        "acq_date": "2022-01-27",
        "lat": -41.87957,
        "lng": -73.80966
    },
    {
        "acq_date": "2022-01-27",
        "lat": -41.400220000000004,
        "lng": -72.91356999999999
    },
    {
        "acq_date": "2022-01-27",
        "lat": -39.37125,
        "lng": -72.62878
    },
    {
        "acq_date": "2022-01-27",
        "lat": -38.3303,
        "lng": -70.99766
    },
    {
        "acq_date": "2022-01-27",
        "lat": -38.25074,
        "lng": -72.59026999999999
    },
    {
        "acq_date": "2022-01-27",
        "lat": -38.21248,
        "lng": -72.47429
    },
    {
        "acq_date": "2022-01-27",
        "lat": -38.195170000000005,
        "lng": -72.41323
    },
    {
        "acq_date": "2022-01-27",
        "lat": -38.10711,
        "lng": -72.43625
    },
    {
        "acq_date": "2022-01-27",
        "lat": -37.969570000000004,
        "lng": -73.21474
    },
    {
        "acq_date": "2022-01-27",
        "lat": -37.87753,
        "lng": -73.12881999999999
    },
    {
        "acq_date": "2022-01-27",
        "lat": -27.89041,
        "lng": -70.19228000000001
    },
    {
        "acq_date": "2022-01-27",
        "lat": -27.12749,
        "lng": -70.16914
    },
    {
        "acq_date": "2022-01-27",
        "lat": -27.03872,
        "lng": -69.88412
    },
    {
        "acq_date": "2022-01-27",
        "lat": -27.04076,
        "lng": -69.89633
    },
    {
        "acq_date": "2022-01-27",
        "lat": -27.03298,
        "lng": -69.9107
    },
    {
        "acq_date": "2022-01-27",
        "lat": -27.02112,
        "lng": -69.90066999999999
    },
    {
        "acq_date": "2022-01-27",
        "lat": -26.59048,
        "lng": -69.96991
    },
    {
        "acq_date": "2022-01-27",
        "lat": -26.592509999999997,
        "lng": -69.98204
    },
    {
        "acq_date": "2022-01-27",
        "lat": -26.382509999999996,
        "lng": -70.07481999999999
    },
    {
        "acq_date": "2022-01-27",
        "lat": -26.37265,
        "lng": -70.07687
    },
    {
        "acq_date": "2022-01-27",
        "lat": -26.3747,
        "lng": -70.08894000000001
    },
    {
        "acq_date": "2022-01-27",
        "lat": -26.315309999999997,
        "lng": -69.85381
    },
    {
        "acq_date": "2022-01-27",
        "lat": -26.31737,
        "lng": -69.86617
    },
    {
        "acq_date": "2022-01-27",
        "lat": -26.31943,
        "lng": -69.87849
    },
    {
        "acq_date": "2022-01-27",
        "lat": -26.309459999999998,
        "lng": -69.88055
    },
    {
        "acq_date": "2022-01-27",
        "lat": -26.317690000000002,
        "lng": -69.92976999999999
    },
    {
        "acq_date": "2022-01-27",
        "lat": -26.277959999999997,
        "lng": -69.93818
    },
    {
        "acq_date": "2022-01-27",
        "lat": -26.284209999999998,
        "lng": -69.97511
    },
    {
        "acq_date": "2022-01-27",
        "lat": -26.2743,
        "lng": -69.97726
    },
    {
        "acq_date": "2022-01-27",
        "lat": -26.20192,
        "lng": -70.10004
    },
    {
        "acq_date": "2022-01-27",
        "lat": -26.19315,
        "lng": -70.10748000000001
    },
    {
        "acq_date": "2022-01-28",
        "lat": -53.758230000000005,
        "lng": -69.87883000000001
    },
    {
        "acq_date": "2022-01-28",
        "lat": -36.86045,
        "lng": -71.37845
    },
    {
        "acq_date": "2022-01-28",
        "lat": -36.862559999999995,
        "lng": -71.36617
    },
    {
        "acq_date": "2022-01-28",
        "lat": -53.75244,
        "lng": -69.87985
    },
    {
        "acq_date": "2022-01-28",
        "lat": -53.754430000000006,
        "lng": -69.86111
    },
    {
        "acq_date": "2022-01-28",
        "lat": -32.8008,
        "lng": -70.94855
    },
    {
        "acq_date": "2022-01-28",
        "lat": -33.43455,
        "lng": -70.79075
    },
    {
        "acq_date": "2022-01-28",
        "lat": -34.107409999999994,
        "lng": -70.45243
    },
    {
        "acq_date": "2022-01-28",
        "lat": -36.65305,
        "lng": -71.09766
    },
    {
        "acq_date": "2022-01-28",
        "lat": -40.56428,
        "lng": -73.17064
    }
]